pyl7vp/__init__.py
pyl7vp/config.py
pyl7vp/engine.py
pyl7vp/l7vp.py
pyl7vp/libs.py
pyl7vp/meta.py
pyl7vp/helper/__init__.py
pyl7vp/helper/code.py
pyl7vp/helper/file.py
pyl7vp/helper/html.py
pyl7vp/helper/merge.py
pyl7vp/templates/l7vp.html
pyl7vp/templates/notebook.html
pyl7vp-0.1.0.dist-info/LICENSE
pyl7vp-0.1.0.dist-info/METADATA
pyl7vp-0.1.0.dist-info/WHEEL
pyl7vp-0.1.0.dist-info/top_level.txt
pyl7vp-0.1.0.dist-info/RECORD
