Metadata-Version: 2.1
Name: pyl7vp
Version: 0.1.0
Summary: Python3 binding for @AntV/L7VP geospatial visual analysis tool.
Home-page: https://github.com/antvis/L7VP/bindings/pyl7vp
Author: @lvisei
Author-email: yunji.me@outlook.com
License: Apache-2.0
Keywords: AntV,L7VP,PyL7VP,visualization,map,geospatial visualization,geospatial analysis
Platform: UNKNOWN
Classifier: Environment :: Console
Classifier: Intended Audience :: Developers
Classifier: License :: OSI Approved :: Apache Software License
Classifier: Operating System :: OS Independent
Classifier: Programming Language :: Python
Classifier: Programming Language :: Python :: 3
Classifier: Programming Language :: Python :: 3.7
Classifier: Programming Language :: Python :: 3.8
Classifier: Programming Language :: Python :: 3.9
Classifier: Topic :: Software Development :: Libraries
License-File: LICENSE
Requires-Dist: jinja2 (>=3.0.0)
Requires-Dist: simplejson
Requires-Dist: pandas (>=1.0.0)
